LMLModLoader
