Metadata-Version: 1.0
Name: LMLModLoader
Version: 0.0.4
Summary: The Required PyPi module for loading Forte Mods.
Home-page: UNKNOWN
Author: UNKNOWN
Author-email: UNKNOWN
License: UNKNOWN
Platform: UNKNOWN
